pyramid_nacl_session/__init__.py
pyramid_nacl_session/scripts.py
pyramid_nacl_session/serializer.py
pyramid_nacl_session/session.py
pyramid_nacl_session/utils.py
pyramid_nacl_session-1.0.0.dist-info/LICENSE.txt
pyramid_nacl_session-1.0.0.dist-info/METADATA
pyramid_nacl_session-1.0.0.dist-info/WHEEL
pyramid_nacl_session-1.0.0.dist-info/entry_points.txt
pyramid_nacl_session-1.0.0.dist-info/top_level.txt
pyramid_nacl_session-1.0.0.dist-info/RECORD
