Metadata-Version: 2.1
Name: pyramid-nacl-session
Version: 1.0.0
Summary: Encrypted session cookie serializer for Pyramid
Home-page: https://github.com/Pylons/pyramid_nacl_session
Author: Agendaless Consulting
Maintainer: Pylons Project
Maintainer-email: pylons-discuss@googlegroups.com
License: BSD-derived (http://www.repoze.org/LICENSE.txt)
Project-URL: Documentation, https://docs.pylonsproject.org/projects/pyramid-nacl-session/en/latest/index.html
Project-URL: Changelog, https://docs.pylonsproject.org/projects/pyramid-nacl-session/en/latest/changes.html
Project-URL: Issue Tracker, https://github.com/Pylons/pyramid_nacl_session/issues
Keywords: pyramid sessions cryptography security
Platform: UNKNOWN
Classifier: Development Status :: 6 - Mature
Classifier: Environment :: Web Environment
Classifier: Framework :: Pyramid
Classifier: Intended Audience :: Developers
Classifier: License :: Repoze Public License
Classifier: Operating System :: OS Independent
Classifier: Programming Language :: Python
Classifier: Programming Language :: Python :: 2
Classifier: Programming Language :: Python :: 2.7
Classifier: Programming Language :: Python :: 3
Classifier: Programming Language :: Python :: 3.5
Classifier: Programming Language :: Python :: 3.6
Classifier: Programming Language :: Python :: 3.7
Classifier: Programming Language :: Python :: 3.8
Classifier: Programming Language :: Python :: Implementation :: CPython
Classifier: Programming Language :: Python :: Implementation :: PyPy
Classifier: Topic :: Internet :: WWW/HTTP
Classifier: Topic :: Internet :: WWW/HTTP :: Session
Classifier: Topic :: Internet :: WWW/HTTP :: WSGI
Classifier: Topic :: Security :: Cryptography
Requires-Python: !=3.0.*,!=3.1.*,!=3.2.*,!=3.3.*,!=3.4.*,>=2.7
Requires-Dist: pyramid (>=1.5)
Requires-Dist: PyNaCl
Provides-Extra: docs
Requires-Dist: Sphinx (>=1.8.1) ; extra == 'docs'
Requires-Dist: pylons-sphinx-themes (>=1.0.9) ; extra == 'docs'
Provides-Extra: testing
Requires-Dist: WebTest ; extra == 'testing'
Requires-Dist: pytest ; extra == 'testing'
Requires-Dist: pytest-cover ; extra == 'testing'
Requires-Dist: coverage (>=5.0) ; extra == 'testing'
